LICENSE
README.md
setup.py
HiveNetSimpleSanic/__init__.py
HiveNetSimpleSanic/auth.py
HiveNetSimpleSanic/server.py
HiveNetSimpleSanic.egg-info/PKG-INFO
HiveNetSimpleSanic.egg-info/SOURCES.txt
HiveNetSimpleSanic.egg-info/dependency_links.txt
HiveNetSimpleSanic.egg-info/not-zip-safe
HiveNetSimpleSanic.egg-info/requires.txt
HiveNetSimpleSanic.egg-info/top_level.txt