Metadata-Version: 2.1
Name: HiveNetSimpleSanic
Version: 0.1.3
Summary: Simplifies the complexity of building restful API based on Sanic.
Home-page: https://github.com/snakeclub/HiveNetAssemble/HiveNetSimpleSanic
Author: 黎慧剑
Author-email: snakeclub@163.com
Maintainer: 黎慧剑
Maintainer-email: snakeclub@163.com
License: Mozilla Public License 2.0
Keywords: HiveNetAssemble HiveNetSimpleSanic Sanic development python lib
Platform: all
Classifier: Operating System :: OS Independent
Classifier: License :: OSI Approved :: Mozilla Public License 2.0 (MPL 2.0)
Classifier: Programming Language :: Python :: 3.8
Classifier: Topic :: Software Development :: Libraries
License-File: LICENSE
